wbsv/__init__.py
wbsv/archiver.py
wbsv/crawler.py
wbsv/main.py
wbsv/py.typed
wbsv/url_filters.py
wbsv/utils.py
wbsv-0.5.4.dist-info/LICENSE
wbsv-0.5.4.dist-info/METADATA
wbsv-0.5.4.dist-info/WHEEL
wbsv-0.5.4.dist-info/entry_points.txt
wbsv-0.5.4.dist-info/top_level.txt
wbsv-0.5.4.dist-info/RECORD
