Metadata-Version: 2.1
Name: wbsv
Version: 0.5.4
Summary: Throw all URIs in a page on to Wayback Machine from CLI.
Home-page: https://github.com/eggplants/wbsv-cli
Author: eggplants
Author-email: w10776e8w@yahoo.co.jp
License: MIT
Platform: UNKNOWN
Classifier: Development Status :: 3 - Alpha
Requires-Python: >=3.8
License-File: LICENSE
Requires-Dist: beautifulsoup4 (>=4.10.0)
Requires-Dist: lxml (>=4.7.1)
Requires-Dist: requests (>=2.27.1)
Requires-Dist: waybackpy (>=3.0.2)
Requires-Dist: types-beautifulsoup4 (>=4.10.14)
Requires-Dist: types-requests (>=2.27.11)
Provides-Extra: dev
Requires-Dist: black (>=21.12b0) ; extra == 'dev'
Requires-Dist: flake8 (>=4.0.1) ; extra == 'dev'
Requires-Dist: isort (>=5.10.1) ; extra == 'dev'
Requires-Dist: mypy (>=0.931) ; extra == 'dev'
Requires-Dist: pytest (>=6.2.5) ; extra == 'dev'
Requires-Dist: types-setuptools (>=57.4.7) ; extra == 'dev'
